flask_sass.py
setup.cfg
setup.py
Flask_Sass.egg-info/PKG-INFO
Flask_Sass.egg-info/SOURCES.txt
Flask_Sass.egg-info/dependency_links.txt
Flask_Sass.egg-info/top_level.txt